AUTHORS
LICENSE
MANIFEST.in
README
VERSION
requirements.txt
setup.py
debug_log.egg-info/PKG-INFO
debug_log.egg-info/SOURCES.txt
debug_log.egg-info/dependency_links.txt
debug_log.egg-info/pbr.json
debug_log.egg-info/top_level.txt
debuglog/__init__.py