Metadata-Version: 1.0
Name: debug-log
Version: 0.3
Summary: debug log
Home-page: https://github.com/lvjiyong
Author: lvjiyong
Author-email: lvjiyong@gmail.com
License: GPL
Platform: any
